simple_good_turing/__init__.py
simple_good_turing/averaging_transform.py
simple_good_turing/sgt.py
simple_good_turing-0.0.3.dist-info/LICENSE
simple_good_turing-0.0.3.dist-info/METADATA
simple_good_turing-0.0.3.dist-info/WHEEL
simple_good_turing-0.0.3.dist-info/top_level.txt
simple_good_turing-0.0.3.dist-info/RECORD
