Metadata-Version: 2.1
Name: simple-good-turing
Version: 0.0.3
Summary: Simple Good-Turing smoothing
Home-page: https://github.com/zack112358/simple-good-turing-estimation
Author: Zachary McCord
Author-email: zjmccord@gmail.com
License: UNKNOWN
Platform: UNKNOWN
Classifier: Programming Language :: Python :: 3
Classifier: License :: OSI Approved :: BSD License
Classifier: Operating System :: OS Independent
Requires-Dist: numpy
Requires-Dist: python-memo
